tilt/__init__.py
tilt/tilt.py
tilt-0.0.5.dist-info/AUTHORS
tilt-0.0.5.dist-info/LICENSE
tilt-0.0.5.dist-info/METADATA
tilt-0.0.5.dist-info/WHEEL
tilt-0.0.5.dist-info/top_level.txt
tilt-0.0.5.dist-info/RECORD
