Metadata-Version: 2.1
Name: tilt
Version: 0.0.5
Summary: A python language binding for the Transparency Information Language and Toolkit (TILT)
Home-page: https://github.com/Transparency-Information-Language/python-tilt
Author: Elias Grünewald
Author-email: gruenewald@tu-berlin.de
License: UNKNOWN
Platform: UNKNOWN
Classifier: Programming Language :: Python :: 3
Classifier: License :: OSI Approved :: MIT License
Classifier: Operating System :: OS Independent
Requires-Python: >=3.6
